{
  "$schema": "http://json-schema.org/draft-07/schema#",
  "$id": "https://gokapi.dev/schemas/filters/okf_dtd.schema.json",
  "$version": "2.0.0",
  "title": "DTD Filter Filter",
  "description": "Configuration for the Okapi DTD Filter Filter",
  "type": "object",
  "x-filter": {
    "id": "okf_dtd",
    "class": "net.sf.okapi.filters.dtd.DTDFilter",
    "extensions": [],
    "mimeTypes": [
      "application/xml+dtd"
    ]
  },
  "properties": {
    "useCodeFinder": {
      "type": "boolean",
      "default": true,
      "description": "Enable pattern-based detection of inline codes (placeholders, tags, etc.)"
    },
    "moveLeadingAndTrailingCodesToSkeleton": {
      "type": "object",
      "description": "Move inline codes at segment boundaries to the skeleton (non-translatable)"
    },
    "mergeAdjacentCodes": {
      "type": "object",
      "description": "Merge consecutive inline codes into a single placeholder"
    },
    "simplifierRules": {
      "type": "string",
      "description": "Rules for simplifying inline code representation",
      "x-widget": "simplifierRulesEditor"
    }
  },
  "additionalProperties": false,
  "x-groups": [
    {
      "id": "inlineCodes",
      "label": "Inline Code Handling",
      "description": "Configure detection and handling of inline codes (placeholders, tags, etc.)",
      "collapsed": true,
      "fields": [
        "useCodeFinder",
        "codeFinderRules",
        "mergeAdjacentCodes",
        "moveLeadingAndTrailingCodesToSkeleton",
        "simplifierRules"
      ]
    }
  ],
  "x-schemaVersion": 2,
  "x-baseVersion": 2,
  "x-baseHash": "e4f5e52404aa",
  "x-compositeHash": "99aab111d82d",
  "x-introducedInOkapi": "1.48.0"
}
