{
  "$schema": "http://json-schema.org/draft-07/schema#",
  "$id": "https://gokapi.dev/schemas/filters/okf_plaintext.schema.json",
  "$version": "1.0.0",
  "title": "Plain Text Filter Filter",
  "description": "Configuration for the Okapi Plain Text Filter Filter",
  "type": "object",
  "x-filter": {
    "id": "okf_plaintext",
    "class": "net.sf.okapi.filters.plaintext.PlainTextFilter",
    "extensions": [],
    "mimeTypes": [
      "text/plain"
    ],
    "configurations": [
      {
        "configId": "okf_plaintext",
        "name": "Plain Text",
        "description": "Plain text files.",
        "mimeType": "text/plain",
        "extensions": ".txt;",
        "isDefault": true
      },
      {
        "configId": "okf_plaintext_trim_trail",
        "name": "Plain Text (Trim Trail)",
        "description": "Text files; trailing spaces and tabs removed from extracted lines.",
        "mimeType": "text/plain",
        "parametersLocation": "okf_plaintext_trim_trail.fprm",
        "isDefault": false
      },
      {
        "configId": "okf_plaintext_trim_all",
        "name": "Plain Text (Trim All)",
        "description": "Text files; leading and trailing spaces and tabs removed from extracted lines.",
        "mimeType": "text/plain",
        "parametersLocation": "okf_plaintext_trim_all.fprm",
        "isDefault": false
      },
      {
        "configId": "okf_plaintext_paragraphs",
        "name": "Plain Text (Paragraphs)",
        "description": "Text files extracted by paragraphs (separated by 1 or more empty lines).",
        "mimeType": "text/plain",
        "parametersLocation": "okf_plaintext_paragraphs.fprm",
        "isDefault": false
      },
      {
        "configId": "okf_plaintext_spliced_backslash",
        "name": "Spliced Lines (Backslash)",
        "description": "Spliced lines filter with the backslash character (\\) used as the splicer.",
        "mimeType": "text/plain",
        "parametersLocation": "okf_plaintext_spliced_backslash.fprm",
        "isDefault": false
      },
      {
        "configId": "okf_plaintext_spliced_underscore",
        "name": "Spliced Lines (Underscore)",
        "description": "Spliced lines filter with the underscore character (_) used as the splicer.",
        "mimeType": "text/plain",
        "parametersLocation": "okf_plaintext_spliced_underscore.fprm",
        "isDefault": false
      },
      {
        "configId": "okf_plaintext_spliced_custom",
        "name": "Spliced Lines (Custom)",
        "description": "Spliced lines filter with a user-defined splicer.",
        "mimeType": "text/plain",
        "parametersLocation": "okf_plaintext_spliced_custom.fprm",
        "isDefault": false
      },
      {
        "configId": "okf_plaintext_regex_lines",
        "name": "Plain Text (Regex, Line=Paragraph)",
        "description": "Plain Text Filter using regex-based linebreak search. Extracts by lines.",
        "mimeType": "text/plain",
        "parametersLocation": "okf_plaintext_regex_lines.fprm",
        "isDefault": false
      },
      {
        "configId": "okf_plaintext_regex_paragraphs",
        "name": "Plain Text (Regex, Block=Paragraph)",
        "description": "Plain Text Filter using regex-based linebreak search. Extracts by paragraphs.",
        "mimeType": "text/plain",
        "parametersLocation": "okf_plaintext_regex_paragraphs.fprm",
        "isDefault": false
      }
    ]
  },
  "properties": {
    "simplifierRules": {
      "type": "string",
      "description": "Simplifier rules for code type normalization",
      "x-widget": "simplifierRulesEditor"
    }
  },
  "additionalProperties": false
}